{
  "brand": "audi",
  "model": "A1",
  "variant": "Sportback 30 TFSI Advanced 5-dr S tronic",
  "price_incl": "492600",
  "source": "quickpic_autospec",
  "scraped_at": "2026-02-24T09:53:55.693890",
  "specifications": {
    "EngineCapacity": "999",
    "PowerKW": "",
    "TorqueNM": "",
    "FuelType": "petrol",
    "Cylinders": "3",
    "Transmission": "7-speed automatic",
    "Drivetrain": "FWD",
    "TopSpeedKMH": "",
    "Acceleration0to100": "",
    "FuelConsumptionL100KM": "",
    "CO2EmissionsGKM": "",
    "LengthMM": "4 029mm",
    "WidthMM": "",
    "HeightMM": "1 409mm",
    "WheelbaseMM": "2 563",
    "BootCapacityL": "",
    "KerbWeightKG": "",
    "FuelTankL": "40",
    "GroundClearanceMM": "",
    "TurningCircleM": "10.50",
    "Airbags": "6",
    "ABS": "std",
    "StabilityControl": "std",
    "Warranty": "Unlimitedkm",
    "ServicePlan": ""
  }
}