{
  "brand": "haval",
  "model": "H6",
  "variant": "2.0T Luxury 9DCT",
  "price_incl": "495500",
  "source": "quickpic_autospec",
  "scraped_at": "2026-02-22T23:42:26.404663",
  "specifications": {
    "EngineCapacity": "1 998",
    "PowerKW": "",
    "TorqueNM": "",
    "FuelType": "petrol",
    "Cylinders": "4",
    "Transmission": "9-speed automatic",
    "Drivetrain": "FWD",
    "TopSpeedKMH": "",
    "Acceleration0to100": "",
    "FuelConsumptionL100KM": "",
    "CO2EmissionsGKM": "",
    "LengthMM": "4 653mm",
    "WidthMM": "1 886",
    "HeightMM": "1 730mm",
    "WheelbaseMM": "2 738",
    "BootCapacityL": "",
    "KerbWeightKG": "",
    "FuelTankL": "60",
    "GroundClearanceMM": "170",
    "TurningCircleM": "",
    "Airbags": "6",
    "ABS": "std",
    "StabilityControl": "std",
    "Warranty": "200 000km",
    "ServicePlan": "7yr/75 000 Kmkm"
  }
}