{
  "brand": "mitsubishi",
  "model": "Pajero Sport",
  "variant": "2.4 Di-D 4x4 Dsl 5-dr A/T",
  "price_incl": "854990",
  "source": "quickpic_autospec",
  "scraped_at": "2026-02-24T10:09:20.315000",
  "specifications": {
    "EngineCapacity": "2 442",
    "PowerKW": "",
    "TorqueNM": "",
    "FuelType": "diesel",
    "Cylinders": "4",
    "Transmission": "8-speed automatic",
    "Drivetrain": "AWD",
    "TopSpeedKMH": "",
    "Acceleration0to100": "",
    "FuelConsumptionL100KM": "",
    "CO2EmissionsGKM": "",
    "LengthMM": "4 825mm",
    "WidthMM": "",
    "HeightMM": "1 805mm",
    "WheelbaseMM": "2 800",
    "BootCapacityL": "",
    "KerbWeightKG": "",
    "FuelTankL": "68",
    "GroundClearanceMM": "218",
    "TurningCircleM": "11.20",
    "Airbags": "7",
    "ABS": "std",
    "StabilityControl": "std",
    "Warranty": "100 000km",
    "ServicePlan": "5yr/90 000 Kmkm"
  }
}